pytorch2ltspice/__init__.py
pytorch2ltspice/pytorch2ltspice.py
pytorch2ltspice/utils/__init__.py
pytorch2ltspice/utils/modelgen.py
pytorch2ltspice/utils/sampling.py
pytorch2ltspice/utils/siggen.py
pytorch2ltspice-0.1.3.dist-info/licenses/LICENSE
pytorch2ltspice-0.1.3.dist-info/METADATA
pytorch2ltspice-0.1.3.dist-info/WHEEL
pytorch2ltspice-0.1.3.dist-info/top_level.txt
pytorch2ltspice-0.1.3.dist-info/RECORD
