Metadata-Version: 2.4
Name: pytorch2ltspice
Version: 0.1.3
Summary: Convert PyTorch neural network models into LTspice subcircuits (.subckt).
Author: kosokno
License: MIT License
Project-URL: Homepage, https://github.com/kosokno/pytorch2ltspice
Project-URL: Repository, https://github.com/kosokno/pytorch2ltspice
Project-URL: Issues, https://github.com/kosokno/pytorch2ltspice/issues
Keywords: ltspice,pytorch,power-electronics,reinforcement-learning,neural-network
Classifier: License :: OSI Approved :: MIT License
Classifier: Programming Language :: Python :: 3
Classifier: Programming Language :: Python :: 3 :: Only
Classifier: Operating System :: OS Independent
Requires-Python: >=3.8
License-File: LICENSE
Requires-Dist: torch
Requires-Dist: numpy
Provides-Extra: dev
Requires-Dist: pytest; extra == "dev"
Requires-Dist: build; extra == "dev"
Requires-Dist: twine; extra == "dev"
Requires-Dist: ruff; extra == "dev"
Dynamic: license-file
